datalinker.py
datalinker-2.1.1.dist-info/LICENSE.txt
datalinker-2.1.1.dist-info/METADATA
datalinker-2.1.1.dist-info/WHEEL
datalinker-2.1.1.dist-info/top_level.txt
datalinker-2.1.1.dist-info/RECORD
