Metadata-Version: 2.1
Name: datalinker
Version: 2.1.1
Summary: Variable sharing mechanism between Python                 fies/folders and across the project/process
Home-page: https://github.com/Satishrajc/datalinker
Author: Satish Chougule
Author-email: satishrajc@gmail.com
License: UNKNOWN
Keywords: DATA SHARING,VARIABLE SHARING,VARIABLE SHARING,SHARINGSHARABLE
Platform: UNKNOWN
Classifier: Programming Language :: Python :: 3
Classifier: License :: OSI Approved :: MIT License
Classifier: Operating System :: OS Independent
Requires-Python: >=3.6
Requires-Dist: deprecation
